ralph/__init__.py
ralph/__main__.py
ralph/app.py
ralph/claude_runner.py
ralph/colors.py
ralph/config.py
ralph/git_manager.py
ralph/harness.py
ralph/harness_runner.py
ralph/prd_manager.py
ralph/spinner.py
ralph/storage.py
ralph/tasks.py
ralph/user_stories.py
ralph/workflow.py
ralph/schemas/ralph_tasks_schema.json
ralph/schemas/task_schema.json
ralph_code-0.5.0.dist-info/licenses/LICENSE
ralph_code-0.5.0.dist-info/METADATA
ralph_code-0.5.0.dist-info/WHEEL
ralph_code-0.5.0.dist-info/entry_points.txt
ralph_code-0.5.0.dist-info/top_level.txt
ralph_code-0.5.0.dist-info/RECORD
