Metadata-Version: 2.4
Name: ralph-code
Version: 0.5.0
Summary: Automated task implementation with Claude Code and Codex
Author: Ralph Coding
License: MIT
Project-URL: Homepage, https://github.com/yourusername/ralph-code
Project-URL: Repository, https://github.com/yourusername/ralph-code
Project-URL: Issues, https://github.com/yourusername/ralph-code/issues
Keywords: claude,codex,ai,automation,coding,cli
Classifier: Development Status :: 3 - Alpha
Classifier: Environment :: Console
Classifier: Intended Audience :: Developers
Classifier: License :: OSI Approved :: MIT License
Classifier: Operating System :: OS Independent
Classifier: Programming Language :: Python :: 3
Classifier: Programming Language :: Python :: 3.10
Classifier: Programming Language :: Python :: 3.11
Classifier: Programming Language :: Python :: 3.12
Classifier: Topic :: Software Development :: Code Generators
Classifier: Topic :: Software Development :: Build Tools
Requires-Python: >=3.10
License-File: LICENSE
Requires-Dist: rich
Requires-Dist: click
Requires-Dist: jsonschema
Requires-Dist: platformdirs
Requires-Dist: questionary
Provides-Extra: dev
Requires-Dist: pytest; extra == "dev"
Requires-Dist: mypy; extra == "dev"
Requires-Dist: types-pygments; extra == "dev"
Requires-Dist: types-jsonschema; extra == "dev"
Dynamic: license-file
Dynamic: requires-python
